HDPACKAGES/__init__.py
HDPACKAGES/python.py
comparingnumber_HarshDhas-1.0.1.dist-info/LICENSE
comparingnumber_HarshDhas-1.0.1.dist-info/METADATA
comparingnumber_HarshDhas-1.0.1.dist-info/WHEEL
comparingnumber_HarshDhas-1.0.1.dist-info/top_level.txt
comparingnumber_HarshDhas-1.0.1.dist-info/RECORD
