Metadata-Version: 2.1
Name: comparingnumber-HarshDhas
Version: 1.0.1
Summary: Helps to find greatest and smallest number among three number
Author: Harshavardhan Manoranjan Dhas
Author-email: Harshavardhan Manoranjan Dhas <dhasharsh@gmail.com>
Project-URL: Homepage, https://github.com/pypa/sampleproject
Project-URL: Bug Tracker, https://github.com/pypa/sampleproject/issues
Classifier: Programming Language :: Python :: 3
Classifier: License :: OSI Approved :: MIT License
Classifier: Operating System :: OS Independent
Requires-Python: >=3.7
License-File: LICENSE
